README.txt
setup.py
hello_rule_set/__init__.py
hello_rule_set/get_rule_set.py
hello_rule_set/rule_tool.py
hello_rule_set/weight_optimization.py
hello_rule_set.egg-info/PKG-INFO
hello_rule_set.egg-info/SOURCES.txt
hello_rule_set.egg-info/dependency_links.txt
hello_rule_set.egg-info/top_level.txt
hello_rule_set.egg-info/zip-safe