Metadata-Version: 1.1
Name: hello-rule-set
Version: 1.5.1
Summary: This is a toolkit that outputs strong rules for the decision engine.
Home-page: https://gitlab.fraudmetrix.cn/yan.wang/ga_weight_optimization
Author: yan.wang
Author-email: 644675188@qq.com
License: MIT
Keywords: rule python package
Platform: UNKNOWN
Classifier: License :: OSI Approved :: MIT License
Classifier: Programming Language :: Python
Classifier: Intended Audience :: Developers
Classifier: Operating System :: OS Independent
